{
  "properties": {
    "displayName": "Storage accounts should use private link (excluding storage accounts managed by Azure Red Hat OpenShift)",
    "policyType": "BuiltIn",
    "mode": "Indexed",
    "description": "Azure Private Link lets you connect your virtual network to Azure services without a public IP address at the source or destination. The Private Link platform handles the connectivity between the consumer and services over the Azure backbone network. By mapping private endpoints to your storage account, data leakage risks are reduced. Learn more about private links at - https://aka.ms/azureprivatelinkoverview. Storage accounts in resource groups managed by ARO are excluded from evaluation.",
    "metadata": {
      "version": "1.0.0",
      "category": "Storage"
    },
    "version": "1.0.0",
    "parameters": {
      "effect": {
        "type": "String",
        "metadata": {
          "displayName": "Effect",
          "description": "Enable or disable the execution of the policy"
        },
        "allowedValues": [
          "AuditIfNotExists",
          "Disabled"
        ],
        "defaultValue": "AuditIfNotExists"
      }
    },
    "policyRule": {
      "if": {
        "allOf": [
          {
            "field": "type",
            "equals": "Microsoft.Storage/storageAccounts"
          },
          {
            "value": "[resourcegroup().managedBy]",
            "notContains": "/providers/Microsoft.RedHatOpenShift/"
          }
        ]
      },
      "then": {
        "effect": "[parameters('effect')]",
        "details": {
          "type": "Microsoft.Storage/storageAccounts/privateEndpointConnections",
          "existenceCondition": {
            "field": "Microsoft.Storage/storageAccounts/privateEndpointConnections/privateLinkServiceConnectionState.status",
            "equals": "Approved"
          }
        }
      }
    },
    "versions": [
      "1.0.0"
    ]
  },
  "id": "/providers/Microsoft.Authorization/policyDefinitions/18ac0011-fb88-42b6-a025-b33b6f0d2cb3",
  "name": "18ac0011-fb88-42b6-a025-b33b6f0d2cb3"
}